Verilog/Decoder/Decoder.v
module Decoder (
	output reg [0:15] Y,
	input [3:0] In);
	
	always @(*) begin
		begin
			case (In)
				4'b0001: Y = 16'b0000000000000001;
				4'b0010: Y = 16'b0000000000000010;
				4'b0011: Y = 16'b0000000000000100;
				4'b0100: Y = 16'b0000000000001000;
				4'b0101: Y = 16'b0000000000010000;
				4'b0110: Y = 16'b0000000000100000;
				4'b0111: Y = 16'b0000000001000000;
				4'b1000: Y = 16'b0000000010000000;
				4'b1001: Y = 16'b0000000100000000;
				4'b1010: Y = 16'b0000001000000000;
				4'b1011: Y = 16'b0000010000000000;
				4'b1100: Y = 16'b0000100000000000;
				4'b1101: Y = 16'b0001000000000000;
				4'b1110: Y = 16'b0010000000000000;
				4'b1111: Y = 16'b0100000000000000;
				default: Y = 16'b0000000000000000;
			endcase
		end
	end
endmodule

Verilog/Decoder/Decoder_Tb.v
module Decoder_Tb; 
	wire [0:15] X;
	reg [3:0] In;

	Decoder Decoder_Dut(X,In);
	initial begin
		#0 In = 4'b0001;
		#2 In = 4'b0010;
		#2 In = 4'b0011;
		#2 In = 4'b0100;
		#2 In = 4'b0101;
		#2 In = 4'b0110;
		#2 In = 4'b0111;
		#2 In = 4'b1000;
		#2 In = 4'b1001;
		#2 In = 4'b1010;
		#2 In = 4'b1011;
		#2 In = 4'b1100;
		#2 In = 4'b1101;
		#2 In = 4'b1110;
		#2 In = 4'b1111;	
		#2 In = 4'b1111;
	end
	initial
	begin
	$dumpfile("Decoder.vcd");	
	$dumpvars(0,Decoder_Dut);
	end
endmodule

Verilog/Decoder/Decoder.vcd
$date
	Fri Oct 14 19:10:35 2022
$end
$version
	Icarus Verilog
$end
$timescale
	1s
$end
$scope module Decoder_Tb $end
$scope module Decoder_Dut $end
$var wire 4 ! In [3:0] $end
$var reg 16 " Y [0:15] $end
$upscope $end
$upscope $end
$enddefinitions $end
#0
$dumpvars
b1 "
b1 !
$end
#2
b10 "
b10 !
#4
b100 "
b11 !
#6
b1000 "
b100 !
#8
b10000 "
b101 !
#10
b100000 "
b110 !
#12
b1000000 "
b111 !
#14
b10000000 "
b1000 !
#16
b100000000 "
b1001 !
#18
b1000000000 "
b1010 !
#20
b10000000000 "
b1011 !
#22
b100000000000 "
b1100 !
#24
b1000000000000 "
b1101 !
#26
b10000000000000 "
b1110 !
#28
b100000000000000 "
b1111 !
