Verilog/Decoder/Decoder.v
module Decoder (
	output reg [0:15] Y,
	input [3:0] In);
	
	always @(*) begin
		begin
			case (In)
				4'b0001: Y = 16'b0000000000000001;
				4'b0010: Y = 16'b0000000000000010;
				4'b0011: Y = 16'b0000000000000100;
				4'b0100: Y = 16'b0000000000001000;
				4'b0101: Y = 16'b0000000000010000;
				4'b0110: Y = 16'b0000000000100000;
				4'b0111: Y = 16'b0000000001000000;
				4'b1000: Y = 16'b0000000010000000;
				4'b1001: Y = 16'b0000000100000000;
				4'b1010: Y = 16'b0000001000000000;
				4'b1011: Y = 16'b0000010000000000;
				4'b1100: Y = 16'b0000100000000000;
				4'b1101: Y = 16'b0001000000000000;
				4'b1110: Y = 16'b0010000000000000;
				4'b1111: Y = 16'b0100000000000000;
				default: Y = 16'b0000000000000000;
			endcase
		end
	end
endmodule

Verilog/Decoder_Tb.v
module Decoder_Tb; 
	wire [0:15] X;
	reg [3:0] In;

	Decoder Decoder_Dut(X,In);
	initial begin
		In = 4'b0001;
		#5 In = 4'b0010;
		#5 In = 4'b0011;
		#5 In = 4'b0100;
		#5 In = 4'b0101;
		#5 In = 4'b0110;
		#5 In = 4'b0111;
		#5 In = 4'b1000;
		#5 In = 4'b1001;
		#5 In = 4'b1010;
		#5 In = 4'b1011;
		#5 In = 4'b1100;
		#5 In = 4'b1101;
		#5 In = 4'b1110;
		#5 In = 4'b1111;	
	end
	initial
	begin
	// $monitor("Y = %b ,#5 In = %b%b; C = %b; D = %b;"X,A,B,C,D);
	$dumpfile("Decoder.vcd");	
	$dumpvars(0,Decoder_Dut);
	end
endmodule

Verilog/Decoder.vcd
$date
	Wed Oct 12 17:35:26 2022
$end
$version
	Icarus Verilog
$end
$timescale
	1s
$end
$scope module Decoder_Tb $end
$scope module Decoder_Dut $end
$var wire 4 ! In [3:0] $end
$var reg 16 " Y [0:15] $end
$upscope $end
$upscope $end
$enddefinitions $end
#0
$dumpvars
b1 "
b1 !
$end
#5
b10 "
b10 !
#10
b100 "
b11 !
#15
b1000 "
b100 !
#20
b10000 "
b101 !
#25
b100000 "
b110 !
#30
b1000000 "
b111 !
#35
b10000000 "
b1000 !
#40
b100000000 "
b1001 !
#45
b1000000000 "
b1010 !
#50
b10000000000 "
b1011 !
#55
b100000000000 "
b1100 !
#60
b1000000000000 "
b1101 !
#65
b10000000000000 "
b1110 !
#70
b100000000000000 "
b1111 !
