Verilog/Encoder/Encoder.v
module Encoder (
	output reg [0:3] Y,
	input [0:15] In);
	
	always @(*) begin
		begin
			case (In)
				16'b0000000000000001: Y = 4'b0001;
				16'b0000000000000010: Y = 4'b0010;
				16'b0000000000000100: Y = 4'b0011;
				16'b0000000000001000: Y = 4'b0100;
				16'b0000000000010000: Y = 4'b0101;
				16'b0000000000100000: Y = 4'b0110;
				16'b0000000001000000: Y = 4'b0111;
				16'b0000000010000000: Y = 4'b1000;
				16'b0000000100000000: Y = 4'b1001;
				16'b0000001000000000: Y = 4'b1010;
				16'b0000010000000000: Y = 4'b1011;
				16'b0000100000000000: Y = 4'b1100;
				16'b0001000000000000: Y = 4'b1101;
				16'b0010000000000000: Y = 4'b1110;
				16'b0100000000000000: Y = 4'b1111;
				default             : Y = 4'b0000;
			endcase
		end
	end
endmodule

Verilog/Encoder_Tb.v
module Encoder_Tb; 
	wire [0:3] X;
	reg [0:15] In;

	Encoder Encoder_Dut(X,In);
	initial begin	
	#0 In = 16'b0000000000000001;
	#5 In = 16'b0000000000000010;
	#5 In = 16'b0000000000000100;
	#5 In = 16'b0000000000001000;
	#5 In = 16'b0000000000010000;
	#5 In = 16'b0000000000100000;
	#5 In = 16'b0000000001000000;
	#5 In = 16'b0000000010000000;
	#5 In = 16'b0000000100000000;
	#5 In = 16'b0000001000000000;
	#5 In = 16'b0000010000000000;
	#5 In = 16'b0000100000000000;
	#5 In = 16'b0001000000000000;
	#5 In = 16'b0010000000000000;
	#5 In = 16'b0100000000000000;
	end
	initial
	begin
	$dumpfile("Encoder.vcd");	
	$dumpvars(0,Encoder_Dut);
	end
endmodule

Verilog/Encoder/Encoder.vcd
$date
	Thu Oct 13 10:26:20 2022
$end
$version
	Icarus Verilog
$end
$timescale
	1s
$end
$scope module Encoder_Tb $end
$scope module Encoder_Dut $end
$var wire 16 ! In [0:15] $end
$var reg 4 " Y [0:3] $end
$upscope $end
$upscope $end
$enddefinitions $end
#0
$dumpvars
b1 "
b1 !
$end
#5
b10 "
b10 !
#10
b11 "
b100 !
#15
b100 "
b1000 !
#20
b101 "
b10000 !
#25
b110 "
b100000 !
#30
b111 "
b1000000 !
#35
b1000 "
b10000000 !
#40
b1001 "
b100000000 !
#45
b1010 "
b1000000000 !
#50
b1011 "
b10000000000 !
#55
b1100 "
b100000000000 !
#60
b1101 "
b1000000000000 !
#65
b1110 "
b10000000000000 !
#70
b1111 "
b100000000000000 !
